google_embed/google.py
google_embed/__init__.py
google_embed-0.1.0.dist-info/top_level.txt
google_embed-0.1.0.dist-info/METADATA
google_embed-0.1.0.dist-info/WHEEL
google_embed-0.1.0.dist-info/pydist.json
google_embed-0.1.0.dist-info/RECORD
google_embed-0.1.0.dist-info/DESCRIPTION.rst
