Metadata-Version: 2.0
Name: google-embed
Version: 0.1.0
Summary: Pelican plugin for embedding Google+ and Google Maps
Home-page: https://github.com/josh146/google_embed
Author: Josh Izaac
Author-email: josh@iza.ac
License: GPLv3
Download-URL: https://github.com/josh146/google_embed/archive/0.1.0.zip
Platform: UNKNOWN
Classifier: Development Status :: 5 - Production/Stable
Classifier: Environment :: Console
Classifier: Intended Audience :: Developers
Classifier: License :: OSI Approved :: GNU General Public License v3 (GPLv3)
Classifier: Natural Language :: English
Classifier: Operating System :: OS Independent
Classifier: Operating System :: MacOS :: MacOS X
Classifier: Operating System :: POSIX :: Linux
Classifier: Programming Language :: Python
Classifier: Topic :: Internet :: WWW/HTTP
Classifier: Topic :: Software Development :: Libraries :: Python Modules
Classifier: Topic :: Text Processing
Provides: google_embed
Requires-Dist: docutils
Requires-Dist: pelican
